{
 "sessions": [
  {
    "carId": "102c20bd-6102-4126-80fb-a9f932ad8c98",
    "chargeDate": "2017/05/14",
    "distanceTraveled": 272.6,
    "energyUsed": 56,
    "maxPossRange": 332,
    "possRange": 282,
    "minPossRange": 230,
    "odometerReading": 415,
    "notes": ""
  },
  {
    "carId": "102c20bd-6102-4126-80fb-a9f932ad8c98",
    "chargeDate": "2017/05/21",
    "distanceTraveled": 132.1,
    "energyUsed": 24.9,
    "maxPossRange": 371,
    "possRange": 315,
    "minPossRange": 258,
    "odometerReading": 547,
    "notes": ""
  },
  {
    "carId": "102c20bd-6102-4126-80fb-a9f932ad8c98",
    "chargeDate": "2017/05/27",
    "distanceTraveled": 127.9,
    "energyUsed": 23.5,
    "maxPossRange": 388,
    "possRange": 329,
    "minPossRange": 269,
    "odometerReading": 675,
    "notes": ""
  },
  {
    "carId": "102c20bd-6102-4126-80fb-a9f932ad8c98",
    "chargeDate": "2017/05/29",
    "distanceTraveled": 69.8,
    "energyUsed": 13.1,
    "maxPossRange": 390,
    "possRange": 331,
    "minPossRange": 271,
    "odometerReading": 744,
    "notes": ""
  },
  {
    "carId": "102c20bd-6102-4126-80fb-a9f932ad8c98",
    "chargeDate": "2017/06/04",
    "distanceTraveled": 131,
    "energyUsed": 23.7,
    "maxPossRange": 401,
    "possRange": 340,
    "minPossRange": 278,
    "odometerReading": 875,
    "notes": ""
  },
  {
    "carId": "102c20bd-6102-4126-80fb-a9f932ad8c98",
    "chargeDate": "2017/06/11",
    "distanceTraveled": 248.7,
    "energyUsed": 47.5,
    "maxPossRange": 379,
    "possRange": 322,
    "minPossRange": 254,
    "odometerReading": 1124,
    "notes": ""
  },
  {
    "carId": "102c20bd-6102-4126-80fb-a9f932ad8c98",
    "chargeDate": "2017/06/17",
    "distanceTraveled": 63,
    "energyUsed": 12.1,
    "maxPossRange": 385,
    "possRange": 327,
    "minPossRange": 268,
    "odometerReading": 1187,
    "notes": ""
  },
  {
    "carId": "102c20bd-6102-4126-80fb-a9f932ad8c98",
    "chargeDate": "2017/07/04",
    "distanceTraveled": 147.2,
    "energyUsed": 28.7,
    "maxPossRange": 397,
    "possRange": 337,
    "minPossRange": 276,
    "odometerReading": 1334,
    "notes": ""
  },
  {
    "carId": "102c20bd-6102-4126-80fb-a9f932ad8c98",
    "chargeDate": "2017/07/05",
    "distanceTraveled": 53,
    "energyUsed": 10,
    "maxPossRange": 371,
    "possRange": 315,
    "minPossRange": 258,
    "odometerReading": 1387,
    "notes": ""
  },
  {
    "carId": "102c20bd-6102-4126-80fb-a9f932ad8c98",
    "chargeDate": "2017/07/07",
    "distanceTraveled": 32.6,
    "energyUsed": 5.6,
    "maxPossRange": 387,
    "possRange": 328,
    "minPossRange": 268,
    "odometerReading": 1420,
    "notes": ""
  },
  {
    "carId": "102c20bd-6102-4126-80fb-a9f932ad8c98",
    "chargeDate": "2017/07/09",
    "distanceTraveled": 105.9,
    "energyUsed": 20.6,
    "maxPossRange": 379,
    "possRange": 322,
    "minPossRange": 264,
    "odometerReading": 1526,
    "notes": ""
  },
  {
    "carId": "102c20bd-6102-4126-80fb-a9f932ad8c98",
    "chargeDate": "2017/07/10",
    "distanceTraveled": 57,
    "energyUsed": 11.3,
    "maxPossRange": 375,
    "possRange": 318,
    "minPossRange": 260,
    "odometerReading": 1583,
    "notes": ""
  },
  {
    "carId": "102c20bd-6102-4126-80fb-a9f932ad8c98",
    "chargeDate": "2017/07/14",
    "distanceTraveled": 58.9,
    "energyUsed": 10.3,
    "maxPossRange": 392,
    "possRange": 333,
    "minPossRange": 273,
    "odometerReading": 1642,
    "notes": ""
  },
  {
    "carId": "102c20bd-6102-4126-80fb-a9f932ad8c98",
    "chargeDate": "2017/07/16",
    "distanceTraveled": 82.6,
    "energyUsed": 15.1,
    "maxPossRange": 395,
    "possRange": 335,
    "minPossRange": 274,
    "odometerReading": 1725,
    "notes": ""
  },
  {
    "carId": "102c20bd-6102-4126-80fb-a9f932ad8c98",
    "chargeDate": "2017/07/17",
    "distanceTraveled": 58.8,
    "energyUsed": 11.8,
    "maxPossRange": 381,
    "possRange": 323,
    "minPossRange": 264,
    "odometerReading": 1784,
    "notes": ""
  },
  {
    "carId": "102c20bd-6102-4126-80fb-a9f932ad8c98",
    "chargeDate": "2017/07/21",
    "distanceTraveled": 51.6,
    "energyUsed": 8.8,
    "maxPossRange": 401,
    "possRange": 340,
    "minPossRange": 278,
    "odometerReading": 1835,
    "notes": ""
  },
  {
    "carId": "102c20bd-6102-4126-80fb-a9f932ad8c98",
    "chargeDate": "2017/07/23",
    "distanceTraveled": 116,
    "energyUsed": 20.1,
    "maxPossRange": 410,
    "possRange": 349,
    "minPossRange": 285,
    "odometerReading": 1951,
    "notes": ""
  },
  {
    "carId": "102c20bd-6102-4126-80fb-a9f932ad8c98",
    "chargeDate": "2017/07/24",
    "distanceTraveled": 55.9,
    "energyUsed": 11.2,
    "maxPossRange": 391,
    "possRange": 332,
    "minPossRange": 272,
    "odometerReading": 2007,
    "notes": ""
  },
  {
    "carId": "102c20bd-6102-4126-80fb-a9f932ad8c98",
    "chargeDate": "2017/07/28",
    "distanceTraveled": 48.5,
    "energyUsed": 8.3,
    "maxPossRange": 409,
    "possRange": 344,
    "minPossRange": 284,
    "odometerReading": 2056,
    "notes": ""
  },
  {
    "carId": "102c20bd-6102-4126-80fb-a9f932ad8c98",
    "chargeDate": "2017/07/30",
    "distanceTraveled": 73,
    "energyUsed": 12.4,
    "maxPossRange": 415,
    "possRange": 352,
    "minPossRange": 288,
    "odometerReading": 2129,
    "notes": ""
  },
  {
    "carId": "102c20bd-6102-4126-80fb-a9f932ad8c98",
    "chargeDate": "2017/07/31",
    "distanceTraveled": 53.5,
    "energyUsed": 10.9,
    "maxPossRange": 392,
    "possRange": 333,
    "minPossRange": 273,
    "odometerReading": 2182,
    "notes": ""
  },
  {
    "carId": "102c20bd-6102-4126-80fb-a9f932ad8c98",
    "chargeDate": "2017/08/04",
    "distanceTraveled": 56.3,
    "energyUsed": 9.5,
    "maxPossRange": 409,
    "possRange": 347,
    "minPossRange": 284,
    "odometerReading": 2239,
    "notes": ""
  },
  {
    "carId": "102c20bd-6102-4126-80fb-a9f932ad8c98",
    "chargeDate": "2017/08/06",
    "distanceTraveled": 103.2,
    "energyUsed": 20,
    "maxPossRange": 394,
    "possRange": 334,
    "minPossRange": 273,
    "odometerReading": 2342,
    "notes": ""
  },
  {
    "carId": "102c20bd-6102-4126-80fb-a9f932ad8c98",
    "chargeDate": "2017/08/07",
    "distanceTraveled": 58.9,
    "energyUsed": 11.8,
    "maxPossRange": 382,
    "possRange": 324,
    "minPossRange": 265,
    "odometerReading": 2401,
    "notes": ""
  },
  {
    "carId": "102c20bd-6102-4126-80fb-a9f932ad8c98",
    "chargeDate": "2017/08/11",
    "distanceTraveled": 49.9,
    "energyUsed": 8.4,
    "maxPossRange": 403,
    "possRange": 342,
    "minPossRange": 280,
    "odometerReading": 2451,
    "notes": ""
  },
  {
    "carId": "102c20bd-6102-4126-80fb-a9f932ad8c98",
    "chargeDate": "2017/08/13",
    "distanceTraveled": 96.3,
    "energyUsed": 16.9,
    "maxPossRange": 408,
    "possRange": 346,
    "minPossRange": 283,
    "odometerReading": 2547,
    "notes": ""
  },
  {
    "carId": "102c20bd-6102-4126-80fb-a9f932ad8c98",
    "chargeDate": "2017/08/14",
    "distanceTraveled": 57.4,
    "energyUsed": 9.9,
    "maxPossRange": 413,
    "possRange": 354,
    "minPossRange": 287,
    "odometerReading": 2604,
    "notes": ""
  },
  {
    "carId": "102c20bd-6102-4126-80fb-a9f932ad8c98",
    "chargeDate": "2017/08/18",
    "distanceTraveled": 51.2,
    "energyUsed": 8.6,
    "maxPossRange": 423,
    "possRange": 359,
    "minPossRange": 294,
    "odometerReading": 2656,
    "notes": ""
  },
  {
    "carId": "102c20bd-6102-4126-80fb-a9f932ad8c98",
    "chargeDate": "2017/08/20",
    "distanceTraveled": 127.8,
    "energyUsed": 21.4,
    "maxPossRange": 429,
    "possRange": 364,
    "minPossRange": 298,
    "odometerReading": 2783,
    "notes": ""
  },
  {
    "carId": "102c20bd-6102-4126-80fb-a9f932ad8c98",
    "chargeDate": "2017/08/21",
    "distanceTraveled": 58.3,
    "energyUsed": 9.5,
    "maxPossRange": 438,
    "possRange": 372,
    "minPossRange": 305,
    "odometerReading": 2844,
    "notes": ""
  },
  {
    "carId": "102c20bd-6102-4126-80fb-a9f932ad8c98",
    "chargeDate": "2017/08/24",
    "distanceTraveled": 49.2,
    "energyUsed": 8.7,
    "maxPossRange": 438,
    "possRange": 372,
    "minPossRange": 305,
    "odometerReading": 2891,
    "notes": ""
  },
  {
    "carId": "102c20bd-6102-4126-80fb-a9f932ad8c98",
    "chargeDate": "2017/09/02",
    "distanceTraveled": 199.8,
    "energyUsed": 37.5,
    "maxPossRange": 410,
    "possRange": 348,
    "minPossRange": 285,
    "odometerReading": 3091,
    "notes": ""
  },
  {
    "carId": "102c20bd-6102-4126-80fb-a9f932ad8c98",
    "chargeDate": "2017/09/03",
    "distanceTraveled": 28.9,
    "energyUsed": 5.6,
    "maxPossRange": 405,
    "possRange": 344,
    "minPossRange": 282,
    "odometerReading": 3120,
    "notes": ""
  },
  {
    "carId": "102c20bd-6102-4126-80fb-a9f932ad8c98",
    "chargeDate": "2017/09/09",
    "distanceTraveled": 137.1,
    "energyUsed": 25.1,
    "maxPossRange": 408,
    "possRange": 347,
    "minPossRange": 285,
    "odometerReading": 3257,
    "notes": ""
  },
  {
    "carId": "102c20bd-6102-4126-80fb-a9f932ad8c98",
    "chargeDate": "2017/09/16",
    "distanceTraveled": 136.5,
    "energyUsed": 24.4,
    "maxPossRange": 411,
    "possRange": 349,
    "minPossRange": 286,
    "odometerReading": 3393,
    "notes": ""
  },
  {
    "carId": "102c20bd-6102-4126-80fb-a9f932ad8c98",
    "chargeDate": "2017/09/23",
    "distanceTraveled": 53.9,
    "energyUsed": 9.5,
    "maxPossRange": 413,
    "possRange": 350,
    "minPossRange": 287,
    "odometerReading": 3447,
    "notes": ""
  },
  {
    "carId": "102c20bd-6102-4126-80fb-a9f932ad8c98",
    "chargeDate": "2017/09/24",
    "distanceTraveled": 127.1,
    "energyUsed": 25,
    "maxPossRange": 379,
    "possRange": 322,
    "minPossRange": 264,
    "odometerReading": 3574,
    "notes": ""
  },
  {
    "carId": "102c20bd-6102-4126-80fb-a9f932ad8c98",
    "chargeDate": "2017/09/30",
    "distanceTraveled": 70.7,
    "energyUsed": 13,
    "maxPossRange": 389,
    "possRange": 330,
    "minPossRange": 270,
    "odometerReading": 3645,
    "notes": ""
  },
  {
    "carId": "102c20bd-6102-4126-80fb-a9f932ad8c98",
    "chargeDate": "2017/09/30",
    "distanceTraveled": 23.8,
    "energyUsed": 4.3,
    "maxPossRange": 391,
    "possRange": 332,
    "minPossRange": 272,
    "odometerReading": 3669,
    "notes": ""
  },
  {
    "carId": "102c20bd-6102-4126-80fb-a9f932ad8c98",
    "chargeDate": "2017/10/02",
    "distanceTraveled": 47.8,
    "energyUsed": 8.7,
    "maxPossRange": 394,
    "possRange": 334,
    "minPossRange": 273,
    "odometerReading": 3717,
    "notes": ""
  },
  {
    "carId": "102c20bd-6102-4126-80fb-a9f932ad8c98",
    "chargeDate": "2017/10/04",
    "distanceTraveled": 167.7,
    "energyUsed": 30.8,
    "maxPossRange": 394,
    "possRange": 334,
    "minPossRange": 273,
    "odometerReading": 3884,
    "notes": ""
  },
  {
    "carId": "102c20bd-6102-4126-80fb-a9f932ad8c98",
    "chargeDate": "2017/10/07",
    "distanceTraveled": 117.1,
    "energyUsed": 21.4,
    "maxPossRange": 395,
    "possRange": 335,
    "minPossRange": 274,
    "odometerReading": 4001,
    "notes": ""
  },
  {
    "carId": "102c20bd-6102-4126-80fb-a9f932ad8c98",
    "chargeDate": "2017/10/28",
    "distanceTraveled": 175.3,
    "energyUsed": 30.3,
    "maxPossRange": 413,
    "possRange": 350,
    "minPossRange": 287,
    "odometerReading": 4177,
    "notes": ""
  },
  {
    "carId": "102c20bd-6102-4126-80fb-a9f932ad8c98",
    "chargeDate": "2017/11/02",
    "distanceTraveled": 95.3,
    "energyUsed": 16.8,
    "maxPossRange": 403,
    "possRange": 342,
    "minPossRange": 280,
    "odometerReading": 4272,
    "notes": ""
  },
  {
    "carId": "102c20bd-6102-4126-80fb-a9f932ad8c98",
    "chargeDate": "2017/11/11",
    "distanceTraveled": 197.1,
    "energyUsed": 37.6,
    "maxPossRange": 387,
    "possRange": 328,
    "minPossRange": 268,
    "odometerReading": 4469,
    "notes": ""
  },
  {
    "carId": "102c20bd-6102-4126-80fb-a9f932ad8c98",
    "chargeDate": "2017/11/18",
    "distanceTraveled": 119.5,
    "energyUsed": 21.6,
    "maxPossRange": 396,
    "possRange": 336,
    "minPossRange": 275,
    "odometerReading": 4588,
    "notes": ""
  },
  {
    "carId": "102c20bd-6102-4126-80fb-a9f932ad8c98",
    "chargeDate": "2017/11/23",
    "distanceTraveled": 87.5,
    "energyUsed": 16.1,
    "maxPossRange": 396,
    "possRange": 336,
    "minPossRange": 275,
    "odometerReading": 4676,
    "notes": ""
  },
  {
    "carId": "102c20bd-6102-4126-80fb-a9f932ad8c98",
    "chargeDate": "2017/11/27",
    "distanceTraveled": 179.3,
    "energyUsed": 34.4,
    "maxPossRange": 381,
    "possRange": 323,
    "minPossRange": 264,
    "odometerReading": 4855,
    "notes": ""
  },
  {
    "carId": "102c20bd-6102-4126-80fb-a9f932ad8c98",
    "chargeDate": "2017/11/30",
    "distanceTraveled": 185.4,
    "energyUsed": 38.5,
    "maxPossRange": 351,
    "possRange": 298,
    "minPossRange": 244,
    "odometerReading": 5041,
    "notes": ""
  },
  {
    "carId": "102c20bd-6102-4126-80fb-a9f932ad8c98",
    "chargeDate": "2017/12/02",
    "distanceTraveled": 162.2,
    "energyUsed": 36.2,
    "maxPossRange": 329,
    "possRange": 279,
    "minPossRange": 228,
    "odometerReading": 5203,
    "notes": ""
  },
  {
    "carId": "102c20bd-6102-4126-80fb-a9f932ad8c98",
    "chargeDate": "2017/12/09",
    "distanceTraveled": 108.9,
    "energyUsed": 20.6,
    "maxPossRange": 355,
    "possRange": 301,
    "minPossRange": 246,
    "odometerReading": 5312,
    "notes": ""
  },
  {
    "carId": "102c20bd-6102-4126-80fb-a9f932ad8c98",
    "chargeDate": "2017/12/25",
    "distanceTraveled": 200.7,
    "energyUsed": 37.1,
    "maxPossRange": 385,
    "possRange": 327,
    "minPossRange": 268,
    "odometerReading": 5513,
    "notes": ""
  },
  {
    "carId": "102c20bd-6102-4126-80fb-a9f932ad8c98",
    "chargeDate": "2018/01/01",
    "distanceTraveled": 114.4,
    "energyUsed": 21,
    "maxPossRange": 389,
    "possRange": 330,
    "minPossRange": 270,
    "odometerReading": 5627,
    "notes": ""
  },
  {
    "carId": "102c20bd-6102-4126-80fb-a9f932ad8c98",
    "chargeDate": "2018/01/07",
    "distanceTraveled": 140.9,
    "energyUsed": 24.4,
    "maxPossRange": 401,
    "possRange": 340,
    "minPossRange": 278,
    "odometerReading": 5768,
    "notes": ""
  },
  {
    "carId": "102c20bd-6102-4126-80fb-a9f932ad8c98",
    "chargeDate": "2018/01/14",
    "distanceTraveled": 133,
    "energyUsed": 23.9,
    "maxPossRange": 401,
    "possRange": 340,
    "minPossRange": 278,
    "odometerReading": 5901,
    "notes": ""
  },
  {
    "carId": "102c20bd-6102-4126-80fb-a9f932ad8c98",
    "chargeDate": "2018/01/15",
    "distanceTraveled": 34.9,
    "energyUsed": 6.7,
    "maxPossRange": 391,
    "possRange": 332,
    "minPossRange": 272,
    "odometerReading": 5936,
    "notes": ""
  },
  {
    "carId": "102c20bd-6102-4126-80fb-a9f932ad8c98",
    "chargeDate": "2018/01/19",
    "distanceTraveled": 181.9,
    "energyUsed": 38.7,
    "maxPossRange": 353,
    "possRange": 300,
    "minPossRange": 246,
    "odometerReading": 6118,
    "notes": ""
  },
  {
    "carId": "102c20bd-6102-4126-80fb-a9f932ad8c98",
    "chargeDate": "2018/01/20",
    "distanceTraveled": 158.2,
    "energyUsed": 36.5,
    "maxPossRange": 324,
    "possRange": 275,
    "minPossRange": 225,
    "odometerReading": 6276,
    "notes": ""
  },
  {
    "carId": "102c20bd-6102-4126-80fb-a9f932ad8c98",
    "chargeDate": "2018/01/21",
    "distanceTraveled": 136.8,
    "energyUsed": 30.5,
    "maxPossRange": 318,
    "possRange": 270,
    "minPossRange": 221,
    "odometerReading": 6413,
    "notes": ""
  },
  {
    "carId": "102c20bd-6102-4126-80fb-a9f932ad8c98",
    "chargeDate": "2018/01/28",
    "distanceTraveled": 84,
    "energyUsed": 15.4,
    "maxPossRange": 351,
    "possRange": 298,
    "minPossRange": 244,
    "odometerReading": 6498,
    "notes": ""
  },
  {
    "carId": "102c20bd-6102-4126-80fb-a9f932ad8c98",
    "chargeDate": "2018/02/01",
    "distanceTraveled": 91.3,
    "energyUsed": 16.1,
    "maxPossRange": 378,
    "possRange": 321,
    "minPossRange": 263,
    "odometerReading": 6588,
    "notes": ""
  },
  {
    "carId": "102c20bd-6102-4126-80fb-a9f932ad8c98",
    "chargeDate": "2018/02/04",
    "distanceTraveled": 48.3,
    "energyUsed": 8.2,
    "maxPossRange": 394,
    "possRange": 334,
    "minPossRange": 273,
    "odometerReading": 6637,
    "notes": ""
  },
  {
    "carId": "102c20bd-6102-4126-80fb-a9f932ad8c98",
    "chargeDate": "2018/02/07",
    "distanceTraveled": 62.7,
    "energyUsed": 10.9,
    "maxPossRange": 400,
    "possRange": 339,
    "minPossRange": 278,
    "odometerReading": 6699,
    "notes": ""
  },
  {
    "carId": "102c20bd-6102-4126-80fb-a9f932ad8c98",
    "chargeDate": "2018/02/11",
    "distanceTraveled": 74.5,
    "energyUsed": 12.6,
    "maxPossRange": 411,
    "possRange": 349,
    "minPossRange": 286,
    "odometerReading": 6774,
    "notes": ""
  },
  {
    "carId": "102c20bd-6102-4126-80fb-a9f932ad8c98",
    "chargeDate": "2018/02/14",
    "distanceTraveled": 64.2,
    "energyUsed": 11.5,
    "maxPossRange": 407,
    "possRange": 345,
    "minPossRange": 282,
    "odometerReading": 6838,
    "notes": ""
  },
  {
    "carId": "102c20bd-6102-4126-80fb-a9f932ad8c98",
    "chargeDate": "2018/02/15",
    "distanceTraveled": 38.7,
    "energyUsed": 6.8,
    "maxPossRange": 407,
    "possRange": 345,
    "minPossRange": 282,
    "odometerReading": 6877,
    "notes": ""
  },
  {
    "carId": "102c20bd-6102-4126-80fb-a9f932ad8c98",
    "chargeDate": "2018/02/24",
    "distanceTraveled": 278,
    "energyUsed": 51.1,
    "maxPossRange": 379,
    "possRange": 322,
    "minPossRange": 264,
    "odometerReading": 7155,
    "notes": ""
  },
  {
    "carId": "102c20bd-6102-4126-80fb-a9f932ad8c98",
    "chargeDate": "2018/02/25",
    "distanceTraveled": 23.3,
    "energyUsed": 4.2,
    "maxPossRange": 379,
    "possRange": 322,
    "minPossRange": 263,
    "odometerReading": 7178,
    "notes": ""
  },
  {
    "carId": "102c20bd-6102-4126-80fb-a9f932ad8c98",
    "chargeDate": "2018/03/03",
    "distanceTraveled": 232.3,
    "energyUsed": 45.8,
    "maxPossRange": 371,
    "possRange": 315,
    "minPossRange": 258,
    "odometerReading": 7410,
    "notes": ""
  },
  {
    "carId": "102c20bd-6102-4126-80fb-a9f932ad8c98",
    "chargeDate": "2018/03/05",
    "distanceTraveled": 50.5,
    "energyUsed": 9.6,
    "maxPossRange": 374,
    "possRange": 317,
    "minPossRange": 259,
    "odometerReading": 7461,
    "notes": ""
  },
  {
    "carId": "102c20bd-6102-4126-80fb-a9f932ad8c98",
    "chargeDate": "2018/03/07",
    "distanceTraveled": 43.8,
    "energyUsed": 7.7,
    "maxPossRange": 381,
    "possRange": 323,
    "minPossRange": 264,
    "odometerReading": 7505,
    "notes": ""
  },
  {
    "carId": "102c20bd-6102-4126-80fb-a9f932ad8c98",
    "chargeDate": "2018/03/11",
    "distanceTraveled": 71.6,
    "energyUsed": 12.3,
    "maxPossRange": 397,
    "possRange": 337,
    "minPossRange": 276,
    "odometerReading": 7576,
    "notes": ""
  },
  {
    "carId": "102c20bd-6102-4126-80fb-a9f932ad8c98",
    "chargeDate": "2018/03/13",
    "distanceTraveled": 47.8,
    "energyUsed": 8.4,
    "maxPossRange": 401,
    "possRange": 340,
    "minPossRange": 278,
    "odometerReading": 7624,
    "notes": ""
  },
  {
    "carId": "102c20bd-6102-4126-80fb-a9f932ad8c98",
    "chargeDate": "2018/03/18",
    "distanceTraveled": 194.2,
    "energyUsed": 36.1,
    "maxPossRange": 385,
    "possRange": 327,
    "minPossRange": 268,
    "odometerReading": 7818,
    "notes": ""
  },
  {
    "carId": "102c20bd-6102-4126-80fb-a9f932ad8c98",
    "chargeDate": "2018/03/20",
    "distanceTraveled": 61.7,
    "energyUsed": 11.6,
    "maxPossRange": 379,
    "possRange": 322,
    "minPossRange": 264,
    "odometerReading": 7880,
    "notes": ""
  },
  {
    "carId": "102c20bd-6102-4126-80fb-a9f932ad8c98",
    "chargeDate": "2018/03/24",
    "distanceTraveled": 46.6,
    "energyUsed": 8.4,
    "maxPossRange": 384,
    "possRange": 326,
    "minPossRange": 267,
    "odometerReading": 7927,
    "notes": ""
  },
  {
    "carId": "102c20bd-6102-4126-80fb-a9f932ad8c98",
    "chargeDate": "2018/03/27",
    "distanceTraveled": 121.3,
    "energyUsed": 22.3,
    "maxPossRange": 387,
    "possRange": 328,
    "minPossRange": 268,
    "odometerReading": 8048,
    "notes": ""
  },
  {
    "carId": "102c20bd-6102-4126-80fb-a9f932ad8c98",
    "chargeDate": "2018/03/31",
    "distanceTraveled": 131.7,
    "energyUsed": 20.8,
    "maxPossRange": 427,
    "possRange": 362,
    "minPossRange": 296,
    "odometerReading": 8180,
    "notes": ""
  },
  {
    "carId": "102c20bd-6102-4126-80fb-a9f932ad8c98",
    "chargeDate": "2018/04/03",
    "distanceTraveled": 83.7,
    "energyUsed": 13.6,
    "maxPossRange": 431,
    "possRange": 366,
    "minPossRange": 300,
    "odometerReading": 8263,
    "notes": ""
  },
  {
    "carId": "102c20bd-6102-4126-80fb-a9f932ad8c98",
    "chargeDate": "2018/04/05",
    "distanceTraveled": 54.9,
    "energyUsed": 9.1,
    "maxPossRange": 429,
    "possRange": 364,
    "minPossRange": 298,
    "odometerReading": 8318,
    "notes": ""
  },
  {
    "carId": "102c20bd-6102-4126-80fb-a9f932ad8c98",
    "chargeDate": "2018/04/08",
    "distanceTraveled": 74.4,
    "energyUsed": 12.3,
    "maxPossRange": 429,
    "possRange": 364,
    "minPossRange": 298,
    "odometerReading": 8393,
    "notes": ""
  },
  {
    "carId": "102c20bd-6102-4126-80fb-a9f932ad8c98",
    "chargeDate": "2018/04/12",
    "distanceTraveled": 75.3,
    "energyUsed": 12.9,
    "maxPossRange": 423,
    "possRange": 359,
    "minPossRange": 294,
    "odometerReading": 8468,
    "notes": ""
  },
  {
    "carId": "102c20bd-6102-4126-80fb-a9f932ad8c98",
    "chargeDate": "2018/04/15",
    "distanceTraveled": 76,
    "energyUsed": 12.1,
    "maxPossRange": 376,
    "possRange": 319,
    "minPossRange": 261,
    "odometerReading": 8545,
    "notes": "software update numbers maybe in error"
  },
  {
    "carId": "102c20bd-6102-4126-80fb-a9f932ad8c98",
    "chargeDate": "2018/04/17",
    "distanceTraveled": 67,
    "energyUsed": 11,
    "maxPossRange": 394,
    "possRange": 334,
    "minPossRange": 273,
    "odometerReading": 8611,
    "notes": ""
  },
  {
    "carId": "102c20bd-6102-4126-80fb-a9f932ad8c98",
    "chargeDate": "2018/04/22",
    "distanceTraveled": 91.9,
    "energyUsed": 14.5,
    "maxPossRange": 417,
    "possRange": 354,
    "minPossRange": 290,
    "odometerReading": 8703,
    "notes": ""
  },
  {
    "carId": "102c20bd-6102-4126-80fb-a9f932ad8c98",
    "chargeDate": "2018/04/29",
    "distanceTraveled": 110.5,
    "energyUsed": 17.2,
    "maxPossRange": 435,
    "possRange": 369,
    "minPossRange": 302,
    "odometerReading": 8814,
    "notes": ""
  },
  {
    "carId": "102c20bd-6102-4126-80fb-a9f932ad8c98",
    "chargeDate": "2018/05/02",
    "distanceTraveled": 57.5,
    "energyUsed": 9.5,
    "maxPossRange": 431,
    "possRange": 366,
    "minPossRange": 300,
    "odometerReading": 8871,
    "notes": ""
  },
  {
    "carId": "102c20bd-6102-4126-80fb-a9f932ad8c98",
    "chargeDate": "2018/05/06",
    "distanceTraveled": 79.4,
    "energyUsed": 12.1,
    "maxPossRange": 438,
    "possRange": 372,
    "minPossRange": 305,
    "odometerReading": 8951,
    "notes": ""
  },
  {
    "carId": "102c20bd-6102-4126-80fb-a9f932ad8c98",
    "chargeDate": "2018/05/09",
    "distanceTraveled": 91,
    "energyUsed": 14.7,
    "maxPossRange": 438,
    "possRange": 372,
    "minPossRange": 305,
    "odometerReading": 9042,
    "notes": ""
  },
  {
    "carId": "102c20bd-6102-4126-80fb-a9f932ad8c98",
    "chargeDate": "2018/05/13",
    "distanceTraveled": 81.5,
    "energyUsed": 12.6,
    "maxPossRange": 438,
    "possRange": 372,
    "minPossRange": 305,
    "odometerReading": 9123,
    "notes": ""
  },
  {
    "carId": "102c20bd-6102-4126-80fb-a9f932ad8c98",
    "chargeDate": "2018/05/16",
    "distanceTraveled": 80,
    "energyUsed": 13,
    "maxPossRange": 438,
    "possRange": 372,
    "minPossRange": 305,
    "odometerReading": 9203,
    "notes": ""
  },
  {
    "carId": "102c20bd-6102-4126-80fb-a9f932ad8c98",
    "chargeDate": "2018/05/20",
    "distanceTraveled": 84.5,
    "energyUsed": 13.3,
    "maxPossRange": 438,
    "possRange": 372,
    "minPossRange": 305,
    "odometerReading": 9288,
    "notes": ""
  },
  {
    "carId": "102c20bd-6102-4126-80fb-a9f932ad8c98",
    "chargeDate": "2018/05/23",
    "distanceTraveled": 76.1,
    "energyUsed": 12.2,
    "maxPossRange": 438,
    "possRange": 372,
    "minPossRange": 305,
    "odometerReading": 9364,
    "notes": ""
  },
  {
    "carId": "102c20bd-6102-4126-80fb-a9f932ad8c98",
    "chargeDate": "2018/05/25",
    "distanceTraveled": 45.1,
    "energyUsed": 6.8,
    "maxPossRange": 438,
    "possRange": 372,
    "minPossRange": 305,
    "odometerReading": 9403,
    "notes": ""
  },
  {
    "carId": "102c20bd-6102-4126-80fb-a9f932ad8c98",
    "chargeDate": "2018/06/03",
    "distanceTraveled": 144.5,
    "energyUsed": 23.3,
    "maxPossRange": 438,
    "possRange": 372,
    "minPossRange": 305,
    "odometerReading": 9553,
    "notes": "software update, possible error total KW in pictures from 06/03 also see 05/25 infotainment system KW off by .2"
  },
  {
    "carId": "102c20bd-6102-4126-80fb-a9f932ad8c98",
    "chargeDate": "2018/06/10",
    "distanceTraveled": 113.7,
    "energyUsed": 18,
    "maxPossRange": 438,
    "possRange": 372,
    "minPossRange": 305,
    "odometerReading": 9667,
    "notes": ""
  },
  {
    "carId": "102c20bd-6102-4126-80fb-a9f932ad8c98",
    "chargeDate": "2018/06/17",
    "distanceTraveled": 53.7,
    "energyUsed": 8.7,
    "maxPossRange": 438,
    "possRange": 372,
    "minPossRange": 305,
    "odometerReading": 9721,
    "notes": ""
  },
  {
    "carId": "102c20bd-6102-4126-80fb-a9f932ad8c98",
    "chargeDate": "2018/07/01",
    "distanceTraveled": 128.3,
    "energyUsed": 21,
    "maxPossRange": 438,
    "possRange": 372,
    "minPossRange": 305,
    "odometerReading": 9849,
    "notes": ""
  },
  {
    "carId": "102c20bd-6102-4126-80fb-a9f932ad8c98",
    "chargeDate": "2018/07/07",
    "distanceTraveled": 181,
    "energyUsed": 28.2,
    "maxPossRange": 438,
    "possRange": 372,
    "minPossRange": 305,
    "odometerReading": 10030,
    "notes": ""
  },
  {
    "carId": "102c20bd-6102-4126-80fb-a9f932ad8c98",
    "chargeDate": "2018/07/19",
    "distanceTraveled": 114.8,
    "energyUsed": 18,
    "maxPossRange": 438,
    "possRange": 372,
    "minPossRange": 305,
    "odometerReading": 10145,
    "notes": ""
  },
  {
    "carId": "102c20bd-6102-4126-80fb-a9f932ad8c98",
    "chargeDate": "2018/07/22",
    "distanceTraveled": 165.7,
    "energyUsed": 28.4,
    "maxPossRange": 420,
    "possRange": 356,
    "minPossRange": 291,
    "odometerReading": 10311,
    "notes": ""
  },
  {
    "carId": "102c20bd-6102-4126-80fb-a9f932ad8c98",
    "chargeDate": "2018/08/19",
    "distanceTraveled": 281.7,
    "energyUsed": 44.9,
    "maxPossRange": 438,
    "possRange": 372,
    "minPossRange": 305,
    "odometerReading": 10592,
    "notes": ""
  },
  {
    "carId": "102c20bd-6102-4126-80fb-a9f932ad8c98",
    "chargeDate": "2018/08/23",
    "distanceTraveled": 147.7,
    "energyUsed": 24.1,
    "maxPossRange": 436,
    "possRange": 370,
    "minPossRange": 303,
    "odometerReading": 10903,
    "notes": ""
  },
  {
    "carId": "102c20bd-6102-4126-80fb-a9f932ad8c98",
    "chargeDate": "2018/09/06",
    "distanceTraveled": 207.3,
    "energyUsed": 37.9,
    "maxPossRange": 411,
    "possRange": 349,
    "minPossRange": 286,
    "odometerReading": 11110,
    "notes": ""
  },
  {
    "carId": "102c20bd-6102-4126-80fb-a9f932ad8c98",
    "chargeDate": "2018/09/13",
    "distanceTraveled": 108.2,
    "energyUsed": 18.2,
    "maxPossRange": 421,
    "possRange": 357,
    "minPossRange": 292,
    "odometerReading": 11218,
    "notes": ""
  },
  {
    "carId": "102c20bd-6102-4126-80fb-a9f932ad8c98",
    "chargeDate": "2018/09/20",
    "distanceTraveled": 91,
    "energyUsed": 15.6,
    "maxPossRange": 418,
    "possRange": 355,
    "minPossRange": 291,
    "odometerReading": 11309,
    "notes": ""
  },
  {
    "carId": "102c20bd-6102-4126-80fb-a9f932ad8c98",
    "chargeDate": "2018/10/04",
    "distanceTraveled": 149.3,
    "energyUsed": 25.4,
    "maxPossRange": 423,
    "possRange": 359,
    "minPossRange": 294,
    "odometerReading": 11459,
    "notes": ""
  },
  {
    "carId": "102c20bd-6102-4126-80fb-a9f932ad8c98",
    "chargeDate": "2018/10/05",
    "distanceTraveled": 45,
    "energyUsed": 8.1,
    "maxPossRange": 414,
    "possRange": 351,
    "minPossRange": 287,
    "odometerReading": 11504,
    "notes": ""
  },
  {
    "carId": "102c20bd-6102-4126-80fb-a9f932ad8c98",
    "chargeDate": "2018/10/08",
    "distanceTraveled": 139.3,
    "energyUsed": 24.8,
    "maxPossRange": 403,
    "possRange": 342,
    "minPossRange": 280,
    "odometerReading": 11643,
    "notes": ""
  },
  {
    "carId": "102c20bd-6102-4126-80fb-a9f932ad8c98",
    "chargeDate": "2018/10/19",
    "distanceTraveled": 122.5,
    "energyUsed": 21,
    "maxPossRange": 418,
    "possRange": 355,
    "minPossRange": 291,
    "odometerReading": 11765,
    "notes": ""
  },
  {
    "carId": "102c20bd-6102-4126-80fb-a9f932ad8c98",
    "chargeDate": "2018/10/22",
    "distanceTraveled": 82.7,
    "energyUsed": 13.4,
    "maxPossRange": 431,
    "possRange": 366,
    "minPossRange": 300,
    "odometerReading": 11848,
    "notes": ""
  },
  {
    "carId": "102c20bd-6102-4126-80fb-a9f932ad8c98",
    "chargeDate": "2018/10/30",
    "distanceTraveled": 80.3,
    "energyUsed": 14.2,
    "maxPossRange": 424,
    "possRange": 360,
    "minPossRange": 295,
    "odometerReading": 11928,
    "notes": ""
  },
  {
    "carId": "102c20bd-6102-4126-80fb-a9f932ad8c98",
    "chargeDate": "2018/11/07",
    "distanceTraveled": 133.9,
    "energyUsed": 22.8,
    "maxPossRange": 429,
    "possRange": 364,
    "minPossRange": 298,
    "odometerReading": 12062,
    "notes": ""
  },
  {
    "carId": "102c20bd-6102-4126-80fb-a9f932ad8c98",
    "chargeDate": "2018/11/14",
    "distanceTraveled": 104.3,
    "energyUsed": 18.7,
    "maxPossRange": 415,
    "possRange": 352,
    "minPossRange": 288,
    "odometerReading": 12167,
    "notes": ""
  },
  {
    "carId": "102c20bd-6102-4126-80fb-a9f932ad8c98",
    "chargeDate": "2018/11/26",
    "distanceTraveled": 218.7,
    "energyUsed": 39.1,
    "maxPossRange": 407,
    "possRange": 345,
    "minPossRange": 282,
    "odometerReading": 12385,
    "notes": ""
  },
  {
    "carId": "102c20bd-6102-4126-80fb-a9f932ad8c98",
    "chargeDate": "2018/11/29",
    "distanceTraveled": 66.4,
    "energyUsed": 11.9,
    "maxPossRange": 402,
    "possRange": 341,
    "minPossRange": 279,
    "odometerReading": 12452,
    "notes": ""
  },
  {
    "carId": "102c20bd-6102-4126-80fb-a9f932ad8c98",
    "chargeDate": "2018/12/04",
    "distanceTraveled": 68,
    "energyUsed": 12.9,
    "maxPossRange": 391,
    "possRange": 332,
    "minPossRange": 272,
    "odometerReading": 12520,
    "notes": ""
  },
  {
    "carId": "102c20bd-6102-4126-80fb-a9f932ad8c98",
    "chargeDate": "2018/12/11",
    "distanceTraveled": 99.5,
    "energyUsed": 18.6,
    "maxPossRange": 385,
    "possRange": 327,
    "minPossRange": 268,
    "odometerReading": 12619,
    "notes": ""
  },
  {
    "carId": "102c20bd-6102-4126-80fb-a9f932ad8c98",
    "chargeDate": "2018/12/14",
    "distanceTraveled": 33.3,
    "energyUsed": 6.1,
    "maxPossRange": 390,
    "possRange": 331,
    "minPossRange": 271,
    "odometerReading": 12653,
    "notes": ""
  },
  {
    "carId": "102c20bd-6102-4126-80fb-a9f932ad8c98",
    "chargeDate": "2018/12/21",
    "distanceTraveled": 97.9,
    "energyUsed": 18,
    "maxPossRange": 388,
    "possRange": 329,
    "minPossRange": 269,
    "odometerReading": 12750,
    "notes": ""
  },
  {
    "carId": "102c20bd-6102-4126-80fb-a9f932ad8c98",
    "chargeDate": "2019/01/02",
    "distanceTraveled": 264.9,
    "energyUsed": 48.4,
    "maxPossRange": 383,
    "possRange": 325,
    "minPossRange": 266,
    "odometerReading": 13015,
    "notes": ""
  },
  {
    "carId": "102c20bd-6102-4126-80fb-a9f932ad8c98",
    "chargeDate": "2019/01/10",
    "distanceTraveled": 73.2,
    "energyUsed": 13.9,
    "maxPossRange": 375,
    "possRange": 318,
    "minPossRange": 260,
    "odometerReading": 13089,
    "notes": ""
  },
  {
    "carId": "102c20bd-6102-4126-80fb-a9f932ad8c98",
    "chargeDate": "2019/01/17",
    "distanceTraveled": 131.8,
    "energyUsed": 24.4,
    "maxPossRange": 381,
    "possRange": 323,
    "minPossRange": 264,
    "odometerReading": 13220,
    "notes": ""
  },
  {
    "carId": "102c20bd-6102-4126-80fb-a9f932ad8c98",
    "chargeDate": "2019/01/22",
    "distanceTraveled": 95.3,
    "energyUsed": 16.7,
    "maxPossRange": 397,
    "possRange": 337,
    "minPossRange": 276,
    "odometerReading": 13316,
    "notes": ""
  },
  {
    "carId": "102c20bd-6102-4126-80fb-a9f932ad8c98",
    "chargeDate": "2019/01/25",
    "distanceTraveled": 54.2,
    "energyUsed": 9.8,
    "maxPossRange": 396,
    "possRange": 336,
    "minPossRange": 275,
    "odometerReading": 13370,
    "notes": ""
  },
  {
    "carId": "102c20bd-6102-4126-80fb-a9f932ad8c98",
    "chargeDate": "2019/02/01",
    "distanceTraveled": 76.2,
    "energyUsed": 13.7,
    "maxPossRange": 400,
    "possRange": 339,
    "minPossRange": 278,
    "odometerReading": 13446,
    "notes": ""
  },
  {
    "carId": "102c20bd-6102-4126-80fb-a9f932ad8c98",
    "chargeDate": "2019/02/05",
    "distanceTraveled": 76.5,
    "energyUsed": 14.6,
    "maxPossRange": 385,
    "possRange": 327,
    "minPossRange": 268,
    "odometerReading": 13523,
    "notes": ""
  },
  {
    "carId": "102c20bd-6102-4126-80fb-a9f932ad8c98",
    "chargeDate": "2019/02/11",
    "distanceTraveled": 158.7,
    "energyUsed": 29.7,
    "maxPossRange": 376,
    "possRange": 319,
    "minPossRange": 261,
    "odometerReading": 13681,
    "notes": ""
  },
  {
    "carId": "102c20bd-6102-4126-80fb-a9f932ad8c98",
    "chargeDate": "2019/02/21",
    "distanceTraveled": 148.4,
    "energyUsed": 28.5,
    "maxPossRange": 369,
    "possRange": 313,
    "minPossRange": 256,
    "odometerReading": 13830,
    "notes": ""
  },
  {
    "carId": "102c20bd-6102-4126-80fb-a9f932ad8c98",
    "chargeDate": "2019/02/28",
    "distanceTraveled": 68.7,
    "energyUsed": 12.4,
    "maxPossRange": 377,
    "possRange": 320,
    "minPossRange": 262,
    "odometerReading": 13898,
    "notes": ""
  },
  {
    "carId": "102c20bd-6102-4126-80fb-a9f932ad8c98",
    "chargeDate": "2019/03/07",
    "distanceTraveled": 95.1,
    "energyUsed": 17,
    "maxPossRange": 384,
    "possRange": 326,
    "minPossRange": 267,
    "odometerReading": 13993,
    "notes": ""
  },
  {
    "carId": "102c20bd-6102-4126-80fb-a9f932ad8c98",
    "chargeDate": "2019/03/14",
    "distanceTraveled": 103.5,
    "energyUsed": 19.4,
    "maxPossRange": 378,
    "possRange": 321,
    "minPossRange": 263,
    "odometerReading": 14097,
    "notes": ""
  },
  {
    "carId": "102c20bd-6102-4126-80fb-a9f932ad8c98",
    "chargeDate": "2019/03/16",
    "distanceTraveled": 31.5,
    "energyUsed": 5.5,
    "maxPossRange": 383,
    "possRange": 325,
    "minPossRange": 266,
    "odometerReading": 14128,
    "notes": ""
  },
  {
    "carId": "102c20bd-6102-4126-80fb-a9f932ad8c98",
    "chargeDate": "2019/03/21",
    "distanceTraveled": 85.3,
    "energyUsed": 14.3,
    "maxPossRange": 402,
    "possRange": 341,
    "minPossRange": 279,
    "odometerReading": 14214,
    "notes": ""
  },
  {
    "carId": "102c20bd-6102-4126-80fb-a9f932ad8c98",
    "chargeDate": "2019/03/28",
    "distanceTraveled": 83.3,
    "energyUsed": 15.2,
    "maxPossRange": 396,
    "possRange": 336,
    "minPossRange": 275,
    "odometerReading": 14297,
    "notes": ""
  },
  {
    "carId": "102c20bd-6102-4126-80fb-a9f932ad8c98",
    "chargeDate": "2019/04/02",
    "distanceTraveled": 135,
    "energyUsed": 23.1,
    "maxPossRange": 407,
    "possRange": 345,
    "minPossRange": 282,
    "odometerReading": 14432,
    "notes": ""
  },
  {
    "carId": "102c20bd-6102-4126-80fb-a9f932ad8c98",
    "chargeDate": "2019/04/05",
    "distanceTraveled": 80.5,
    "energyUsed": 14.2,
    "maxPossRange": 409,
    "possRange": 347,
    "minPossRange": 284,
    "odometerReading": 14512,
    "notes": ""
  },
  {
    "carId": "102c20bd-6102-4126-80fb-a9f932ad8c98",
    "chargeDate": "2019/04/08",
    "distanceTraveled": 138,
    "energyUsed": 22.9,
    "maxPossRange": 418,
    "possRange": 355,
    "minPossRange": 291,
    "odometerReading": 14650,
    "notes": ""
  },
  {
    "carId": "102c20bd-6102-4126-80fb-a9f932ad8c98",
    "chargeDate": "2019/04/11",
    "distanceTraveled": 82.2,
    "energyUsed": 14.3,
    "maxPossRange": 413,
    "possRange": 350,
    "minPossRange": 287,
    "odometerReading": 14733,
    "notes": ""
  },
  {
    "carId": "102c20bd-6102-4126-80fb-a9f932ad8c98",
    "chargeDate": "2019/04/18",
    "distanceTraveled": 105.3,
    "energyUsed": 17.9,
    "maxPossRange": 420,
    "possRange": 356,
    "minPossRange": 291,
    "odometerReading": 14838,
    "notes": ""
  },
  {
    "carId": "102c20bd-6102-4126-80fb-a9f932ad8c98",
    "chargeDate": "2019/04/26",
    "distanceTraveled": 154.6,
    "energyUsed": 25.8,
    "maxPossRange": 427,
    "possRange": 362,
    "minPossRange": 296,
    "odometerReading": 14993,
    "notes": ""
  },
  {
    "carId": "102c20bd-6102-4126-80fb-a9f932ad8c98",
    "chargeDate": "2019/05/02",
    "distanceTraveled": 144.7,
    "energyUsed": 23.9,
    "maxPossRange": 430,
    "possRange": 365,
    "minPossRange": 299,
    "odometerReading": 15137,
    "notes": ""
  },
  {
    "carId": "102c20bd-6102-4126-80fb-a9f932ad8c98",
    "chargeDate": "2019/05/09",
    "distanceTraveled": 215,
    "energyUsed": 37.5,
    "maxPossRange": 409,
    "possRange": 347,
    "minPossRange": 284,
    "odometerReading": 15352,
    "notes": ""
  },
  {
    "carId": "102c20bd-6102-4126-80fb-a9f932ad8c98",
    "chargeDate": "2019/05/16",
    "distanceTraveled": 120,
    "energyUsed": 20.2,
    "maxPossRange": 415,
    "possRange": 352,
    "minPossRange": 288,
    "odometerReading": 15472,
    "notes": ""
  },
  {
    "carId": "102c20bd-6102-4126-80fb-a9f932ad8c98",
    "chargeDate": "2019/05/23",
    "distanceTraveled": 112,
    "energyUsed": 19.6,
    "maxPossRange": 409,
    "possRange": 347,
    "minPossRange": 284,
    "odometerReading": 15584,
    "notes": ""
  },
  {
    "carId": "102c20bd-6102-4126-80fb-a9f932ad8c98",
    "chargeDate": "2019/05/30",
    "distanceTraveled": 160.3,
    "energyUsed": 26.2,
    "maxPossRange": 427,
    "possRange": 362,
    "minPossRange": 296,
    "odometerReading": 15745,
    "notes": ""
  },
  {
    "carId": "102c20bd-6102-4126-80fb-a9f932ad8c98",
    "chargeDate": "2019/06/06",
    "distanceTraveled": 141,
    "energyUsed": 22.7,
    "maxPossRange": 435,
    "possRange": 369,
    "minPossRange": 302,
    "odometerReading": 15886,
    "notes": ""
  },
  {
    "carId": "102c20bd-6102-4126-80fb-a9f932ad8c98",
    "chargeDate": "2019/06/13",
    "distanceTraveled": 126,
    "energyUsed": 21.7,
    "maxPossRange": 434,
    "possRange": 368,
    "minPossRange": 301,
    "odometerReading": 16012,
    "notes": ""
  },
  {
    "carId": "102c20bd-6102-4126-80fb-a9f932ad8c98",
    "chargeDate": "2019/06/20",
    "distanceTraveled": 121.2,
    "energyUsed": 19.7,
    "maxPossRange": 434,
    "possRange": 368,
    "minPossRange": 301,
    "odometerReading": 16133,
    "notes": ""
  },
  {
    "carId": "102c20bd-6102-4126-80fb-a9f932ad8c98",
    "chargeDate": "2019/06/27",
    "distanceTraveled": 96.9,
    "energyUsed": 15.9,
    "maxPossRange": 431,
    "possRange": 366,
    "minPossRange": 300,
    "odometerReading": 16230,
    "notes": ""
  },
  {
    "carId": "102c20bd-6102-4126-80fb-a9f932ad8c98",
    "chargeDate": "2019/07/03",
    "distanceTraveled": 175.6,
    "energyUsed": 33.2,
    "maxPossRange": 388,
    "possRange": 329,
    "minPossRange": 269,
    "odometerReading": 16405,
    "notes": ""
  },
  {
    "carId": "102c20bd-6102-4126-80fb-a9f932ad8c98",
    "chargeDate": "2019/07/11",
    "distanceTraveled": 118.5,
    "energyUsed": 19.5,
    "maxPossRange": 416,
    "possRange": 353,
    "minPossRange": 289,
    "odometerReading": 16524,
    "notes": ""
  },
  {
    "carId": "102c20bd-6102-4126-80fb-a9f932ad8c98",
    "chargeDate": "2019/07/18",
    "distanceTraveled": 107.6,
    "energyUsed": 17.6,
    "maxPossRange": 424,
    "possRange": 360,
    "minPossRange": 295,
    "odometerReading": 16632,
    "notes": ""
  },
  {
    "carId": "102c20bd-6102-4126-80fb-a9f932ad8c98",
    "chargeDate": "2019/07/25",
    "distanceTraveled": 145.7,
    "energyUsed": 24.4,
    "maxPossRange": 417,
    "possRange": 354,
    "minPossRange": 290,
    "odometerReading": 16777,
    "notes": ""
  },
  {
    "carId": "102c20bd-6102-4126-80fb-a9f932ad8c98",
    "chargeDate": "2019/08/08",
    "distanceTraveled": 162.9,
    "energyUsed": 26.6,
    "maxPossRange": 429,
    "possRange": 364,
    "minPossRange": 298,
    "odometerReading": 16940,
    "notes": ""
  },
  {
    "carId": "102c20bd-6102-4126-80fb-a9f932ad8c98",
    "chargeDate": "2019/08/15",
    "distanceTraveled": 118.3,
    "energyUsed": 19.1,
    "maxPossRange": 438,
    "possRange": 372,
    "minPossRange": 305,
    "odometerReading": 17058,
    "notes": ""
  },
  {
    "carId": "102c20bd-6102-4126-80fb-a9f932ad8c98",
    "chargeDate": "2019/08/22",
    "distanceTraveled": 125.4,
    "energyUsed": 22.6,
    "maxPossRange": 424,
    "possRange": 360,
    "minPossRange": 295,
    "odometerReading": 17184,
    "notes": ""
  },
  {
    "carId": "102c20bd-6102-4126-80fb-a9f932ad8c98",
    "chargeDate": "2019/08/29",
    "distanceTraveled": 93.6,
    "energyUsed": 15.1,
    "maxPossRange": 434,
    "possRange": 368,
    "minPossRange": 301,
    "odometerReading": 17277,
    "notes": ""
  },
  {
    "carId": "102c20bd-6102-4126-80fb-a9f932ad8c98",
    "chargeDate": "2019/09/04",
    "distanceTraveled": 120.3,
    "energyUsed": 19.6,
    "maxPossRange": 438,
    "possRange": 372,
    "minPossRange": 305,
    "odometerReading": 17398,
    "notes": ""
  },
  {
    "carId": "102c20bd-6102-4126-80fb-a9f932ad8c98",
    "chargeDate": "2019/09/05",
    "distanceTraveled": 109.8,
    "energyUsed": 18.5,
    "maxPossRange": 429,
    "possRange": 364,
    "minPossRange": 298,
    "odometerReading": 17508,
    "notes": ""
  },
  {
    "carId": "102c20bd-6102-4126-80fb-a9f932ad8c98",
    "chargeDate": "2019/09/12",
    "distanceTraveled": 109.1,
    "energyUsed": 17.8,
    "maxPossRange": 436,
    "possRange": 370,
    "minPossRange": 303,
    "odometerReading": 17617,
    "notes": ""
  },
  {
    "carId": "102c20bd-6102-4126-80fb-a9f932ad8c98",
    "chargeDate": "2019/09/19",
    "distanceTraveled": 122.3,
    "energyUsed": 20.9,
    "maxPossRange": 422,
    "possRange": 358,
    "minPossRange": 293,
    "odometerReading": 17739,
    "notes": ""
  },
  {
    "carId": "102c20bd-6102-4126-80fb-a9f932ad8c98",
    "chargeDate": "2019/09/27",
    "distanceTraveled": 117.9,
    "energyUsed": 19.1,
    "maxPossRange": 434,
    "possRange": 368,
    "minPossRange": 301,
    "odometerReading": 17857,
    "notes": ""
  },
  {
    "carId": "102c20bd-6102-4126-80fb-a9f932ad8c98",
    "chargeDate": "2019/10/03",
    "distanceTraveled": 90.6,
    "energyUsed": 15.7,
    "maxPossRange": 423,
    "possRange": 359,
    "minPossRange": 294,
    "odometerReading": 17948,
    "notes": ""
  },
  {
    "carId": "102c20bd-6102-4126-80fb-a9f932ad8c98",
    "chargeDate": "2019/10/09",
    "distanceTraveled": 114.4,
    "energyUsed": 18.3,
    "maxPossRange": 437,
    "possRange": 371,
    "minPossRange": 304,
    "odometerReading": 18062,
    "notes": ""
  },
  {
    "carId": "102c20bd-6102-4126-80fb-a9f932ad8c98",
    "chargeDate": "2019/10/17",
    "distanceTraveled": 132.9,
    "energyUsed": 22.3,
    "maxPossRange": 429,
    "possRange": 364,
    "minPossRange": 298,
    "odometerReading": 18195,
    "notes": ""
  },
  {
    "carId": "102c20bd-6102-4126-80fb-a9f932ad8c98",
    "chargeDate": "2019/10/24",
    "distanceTraveled": 72.6,
    "energyUsed": 12.5,
    "maxPossRange": 425,
    "possRange": 361,
    "minPossRange": 296,
    "odometerReading": 18267,
    "notes": ""
  },
  {
    "carId": "102c20bd-6102-4126-80fb-a9f932ad8c98",
    "chargeDate": "2019/10/31",
    "distanceTraveled": 95.5,
    "energyUsed": 16.6,
    "maxPossRange": 420,
    "possRange": 356,
    "minPossRange": 291,
    "odometerReading": 18363,
    "notes": ""
  }
]
}
